[
    {
        "Description": "FirstDoseDelta",
        "Value": "12880",
        "Population": "",
        "FirstDose": "",
        "PercentageFirstDose": "",
        "SecondDose": "",
        "PercentageSecondDose": "",
        "SingleDose": null,
        "PercentageSingleDose": null,
        "AtLeastOneVaccine": null,
        "PercentAtLeastOneVaccine": null,
        "FullyVaccinated": null,
        "PercentFullyVaccinated": null
    },
    {
        "Description": "SecondDoseDelta",
        "Value": "26476",
        "Population": "",
        "FirstDose": "",
        "PercentageFirstDose": "",
        "SecondDose": "",
        "PercentageSecondDose": "",
        "SingleDose": null,
        "PercentageSingleDose": null,
        "AtLeastOneVaccine": null,
        "PercentAtLeastOneVaccine": null,
        "FullyVaccinated": null,
        "PercentFullyVaccinated": null
    },
    {
        "Description": "SingleDoseDelta",
        "Value": "1073",
        "Population": "",
        "FirstDose": "",
        "PercentageFirstDose": "",
        "SecondDose": "",
        "PercentageSecondDose": "",
        "SingleDose": null,
        "PercentageSingleDose": null,
        "AtLeastOneVaccine": null,
        "PercentAtLeastOneVaccine": null,
        "FullyVaccinated": null,
        "PercentFullyVaccinated": null
    },
    {
        "Description": "FirstDoseDelivered",
        "Value": "0",
        "Population": "",
        "FirstDose": "",
        "PercentageFirstDose": "",
        "SecondDose": "",
        "PercentageSecondDose": "",
        "SingleDose": null,
        "PercentageSingleDose": null,
        "AtLeastOneVaccine": null,
        "PercentAtLeastOneVaccine": null,
        "FullyVaccinated": null,
        "PercentFullyVaccinated": null
    },
    {
        "Description": "SecondDoseDelivered",
        "Value": "0",
        "Population": "",
        "FirstDose": "",
        "PercentageFirstDose": "",
        "SecondDose": "",
        "PercentageSecondDose": "",
        "SingleDose": null,
        "PercentageSingleDose": null,
        "AtLeastOneVaccine": null,
        "PercentAtLeastOneVaccine": null,
        "FullyVaccinated": null,
        "PercentFullyVaccinated": null
    },
    {
        "Description": "TotalSingleDoseDelivered",
        "Value": "0",
        "Population": "",
        "FirstDose": "",
        "PercentageFirstDose": "",
        "SecondDose": "",
        "PercentageSecondDose": "",
        "SingleDose": null,
        "PercentageSingleDose": null,
        "AtLeastOneVaccine": null,
        "PercentAtLeastOneVaccine": null,
        "FullyVaccinated": null,
        "PercentFullyVaccinated": null
    },
    {
        "Description": "TotalVaccineDosesDelivered",
        "Value": "8520220",
        "Population": "",
        "FirstDose": "",
        "PercentageFirstDose": "",
        "SecondDose": "",
        "PercentageSecondDose": "",
        "SingleDose": null,
        "PercentageSingleDose": null,
        "AtLeastOneVaccine": null,
        "PercentAtLeastOneVaccine": null,
        "FullyVaccinated": null,
        "PercentFullyVaccinated": null
    },
    {
        "Description": "FirstDoseDistributed",
        "Value": "3425361",
        "Population": "",
        "FirstDose": "",
        "PercentageFirstDose": "",
        "SecondDose": "",
        "PercentageSecondDose": "",
        "SingleDose": null,
        "PercentageSingleDose": null,
        "AtLeastOneVaccine": null,
        "PercentAtLeastOneVaccine": null,
        "FullyVaccinated": null,
        "PercentFullyVaccinated": null
    },
    {
        "Description": "FirstDosePercentVaccinated",
        "Value": "56.658",
        "Population": "",
        "FirstDose": "",
        "PercentageFirstDose": "",
        "SecondDose": "",
        "PercentageSecondDose": "",
        "SingleDose": null,
        "PercentageSingleDose": null,
        "AtLeastOneVaccine": null,
        "PercentAtLeastOneVaccine": null,
        "FullyVaccinated": null,
        "PercentFullyVaccinated": null
    },
    {
        "Description": "SecondDoseCumulative",
        "Value": "3072973",
        "Population": "",
        "FirstDose": "",
        "PercentageFirstDose": "",
        "SecondDose": "",
        "PercentageSecondDose": "",
        "SingleDose": null,
        "PercentageSingleDose": null,
        "AtLeastOneVaccine": null,
        "PercentAtLeastOneVaccine": null,
        "FullyVaccinated": null,
        "PercentFullyVaccinated": null
    },
    {
        "Description": "SecondDosePercentVaccinated",
        "Value": "50.829",
        "Population": "",
        "FirstDose": "",
        "PercentageFirstDose": "",
        "SecondDose": "",
        "PercentageSecondDose": "",
        "SingleDose": null,
        "PercentageSingleDose": null,
        "AtLeastOneVaccine": null,
        "PercentAtLeastOneVaccine": null,
        "FullyVaccinated": null,
        "PercentFullyVaccinated": null
    },
    {
        "Description": "SingleDoseDistributed",
        "Value": "257029",
        "Population": "",
        "FirstDose": "",
        "PercentageFirstDose": "",
        "SecondDose": "",
        "PercentageSecondDose": "",
        "SingleDose": null,
        "PercentageSingleDose": null,
        "AtLeastOneVaccine": null,
        "PercentAtLeastOneVaccine": null,
        "FullyVaccinated": null,
        "PercentFullyVaccinated": null
    },
    {
        "Description": "SingleDosePercentVaccinated",
        "Value": "4.251",
        "Population": "",
        "FirstDose": "",
        "PercentageFirstDose": "",
        "SecondDose": "",
        "PercentageSecondDose": "",
        "SingleDose": null,
        "PercentageSingleDose": null,
        "AtLeastOneVaccine": null,
        "PercentAtLeastOneVaccine": null,
        "FullyVaccinated": null,
        "PercentFullyVaccinated": null
    },
    {
        "Description": "FirstSecondSingleDistributed",
        "Value": "6755363",
        "Population": "",
        "FirstDose": "",
        "PercentageFirstDose": "",
        "SecondDose": "",
        "PercentageSecondDose": "",
        "SingleDose": null,
        "PercentageSingleDose": null,
        "AtLeastOneVaccine": null,
        "PercentAtLeastOneVaccine": null,
        "FullyVaccinated": null,
        "PercentFullyVaccinated": null
    },
    {
        "Description": "FirstSecondSinglePercentVaccinated",
        "Value": "111.739",
        "Population": "",
        "FirstDose": "",
        "PercentageFirstDose": "",
        "SecondDose": "",
        "PercentageSecondDose": "",
        "SingleDose": null,
        "PercentageSingleDose": null,
        "AtLeastOneVaccine": null,
        "PercentAtLeastOneVaccine": null,
        "FullyVaccinated": null,
        "PercentFullyVaccinated": null
    },
    {
        "Description": "VaxCompletedDistributed",
        "Value": "3330002",
        "Population": "",
        "FirstDose": "",
        "PercentageFirstDose": "",
        "SecondDose": "",
        "PercentageSecondDose": "",
        "SingleDose": null,
        "PercentageSingleDose": null,
        "AtLeastOneVaccine": null,
        "PercentAtLeastOneVaccine": null,
        "FullyVaccinated": null,
        "PercentFullyVaccinated": null
    },
    {
        "Description": "FullyVaxCumulativePercentVaccinated",
        "Value": "55.081",
        "Population": "",
        "FirstDose": "",
        "PercentageFirstDose": "",
        "SecondDose": "",
        "PercentageSecondDose": "",
        "SingleDose": null,
        "PercentageSingleDose": null,
        "AtLeastOneVaccine": null,
        "PercentAtLeastOneVaccine": null,
        "FullyVaccinated": null,
        "PercentFullyVaccinated": null
    },
    {
        "Description": "EighteenPlusAtLeastOneDose",
        "Value": "73.6",
        "Population": "",
        "FirstDose": "",
        "PercentageFirstDose": "",
        "SecondDose": "",
        "PercentageSecondDose": "",
        "SingleDose": null,
        "PercentageSingleDose": null,
        "AtLeastOneVaccine": null,
        "PercentAtLeastOneVaccine": null,
        "FullyVaccinated": null,
        "PercentFullyVaccinated": null
    },
    {
        "Description": "Allegany",
        "Value": "",
        "Population": "",
        "FirstDose": "26425",
        "PercentageFirstDose": "37.527",
        "SecondDose": "24349",
        "PercentageSecondDose": "34.579",
        "SingleDose": "2870",
        "PercentageSingleDose": "4.076",
        "AtLeastOneVaccine": "29295.0",
        "PercentAtLeastOneVaccine": "41.603",
        "FullyVaccinated": "27219.0",
        "PercentFullyVaccinated": "38.655"
    },
    {
        "Description": "Anne Arundel",
        "Value": "",
        "Population": "",
        "FirstDose": "307637",
        "PercentageFirstDose": "53.111",
        "SecondDose": "279729",
        "PercentageSecondDose": "48.293",
        "SingleDose": "21513",
        "PercentageSingleDose": "3.714",
        "AtLeastOneVaccine": "329150.0",
        "PercentAtLeastOneVaccine": "56.825",
        "FullyVaccinated": "301242.0",
        "PercentFullyVaccinated": "52.007"
    },
    {
        "Description": "Baltimore",
        "Value": "",
        "Population": "",
        "FirstDose": "445638",
        "PercentageFirstDose": "53.862",
        "SecondDose": "403514",
        "PercentageSecondDose": "48.771",
        "SingleDose": "32753",
        "PercentageSingleDose": "3.959",
        "AtLeastOneVaccine": "478391.0",
        "PercentAtLeastOneVaccine": "57.821",
        "FullyVaccinated": "436267.0",
        "PercentFullyVaccinated": "52.729"
    },
    {
        "Description": "Baltimore City",
        "Value": "",
        "Population": "",
        "FirstDose": "269848",
        "PercentageFirstDose": "45.468",
        "SecondDose": "238064",
        "PercentageSecondDose": "40.113",
        "SingleDose": "17052",
        "PercentageSingleDose": "2.873",
        "AtLeastOneVaccine": "286900.0",
        "PercentAtLeastOneVaccine": "48.341",
        "FullyVaccinated": "255116.0",
        "PercentFullyVaccinated": "42.986"
    },
    {
        "Description": "Calvert",
        "Value": "",
        "Population": "",
        "FirstDose": "46502",
        "PercentageFirstDose": "50.259",
        "SecondDose": "42722",
        "PercentageSecondDose": "46.173",
        "SingleDose": "3300",
        "PercentageSingleDose": "3.567",
        "AtLeastOneVaccine": "49802.0",
        "PercentAtLeastOneVaccine": "53.825",
        "FullyVaccinated": "46022.0",
        "PercentFullyVaccinated": "49.74"
    },
    {
        "Description": "Caroline",
        "Value": "",
        "Population": "",
        "FirstDose": "12119",
        "PercentageFirstDose": "36.278",
        "SecondDose": "11102",
        "PercentageSecondDose": "33.234",
        "SingleDose": "2788",
        "PercentageSingleDose": "8.346",
        "AtLeastOneVaccine": "14907.0",
        "PercentAtLeastOneVaccine": "44.624",
        "FullyVaccinated": "13890.0",
        "PercentFullyVaccinated": "41.579"
    },
    {
        "Description": "Carroll",
        "Value": "",
        "Population": "",
        "FirstDose": "87993",
        "PercentageFirstDose": "52.238",
        "SecondDose": "81256",
        "PercentageSecondDose": "48.238",
        "SingleDose": "8706",
        "PercentageSingleDose": "5.168",
        "AtLeastOneVaccine": "96699.0",
        "PercentAtLeastOneVaccine": "57.406",
        "FullyVaccinated": "89962.0",
        "PercentFullyVaccinated": "53.407"
    },
    {
        "Description": "Cecil",
        "Value": "",
        "Population": "",
        "FirstDose": "39818",
        "PercentageFirstDose": "38.713",
        "SecondDose": "36101",
        "PercentageSecondDose": "35.099",
        "SingleDose": "2993",
        "PercentageSingleDose": "2.91",
        "AtLeastOneVaccine": "42811.0",
        "PercentAtLeastOneVaccine": "41.623",
        "FullyVaccinated": "39094.0",
        "PercentFullyVaccinated": "38.009"
    },
    {
        "Description": "Charles",
        "Value": "",
        "Population": "",
        "FirstDose": "74868",
        "PercentageFirstDose": "45.859",
        "SecondDose": "67700",
        "PercentageSecondDose": "41.468",
        "SingleDose": "4643",
        "PercentageSingleDose": "2.844",
        "AtLeastOneVaccine": "79511.0",
        "PercentAtLeastOneVaccine": "48.703",
        "FullyVaccinated": "72343.0",
        "PercentFullyVaccinated": "44.312"
    },
    {
        "Description": "Dorchester",
        "Value": "",
        "Population": "",
        "FirstDose": "12742",
        "PercentageFirstDose": "39.907",
        "SecondDose": "11475",
        "PercentageSecondDose": "35.939",
        "SingleDose": "2064",
        "PercentageSingleDose": "6.464",
        "AtLeastOneVaccine": "14806.0",
        "PercentAtLeastOneVaccine": "46.372",
        "FullyVaccinated": "13539.0",
        "PercentFullyVaccinated": "42.403"
    },
    {
        "Description": "Frederick",
        "Value": "",
        "Population": "",
        "FirstDose": "141150",
        "PercentageFirstDose": "54.383",
        "SecondDose": "128855",
        "PercentageSecondDose": "49.646",
        "SingleDose": "15507",
        "PercentageSingleDose": "5.975",
        "AtLeastOneVaccine": "156657.0",
        "PercentAtLeastOneVaccine": "60.358",
        "FullyVaccinated": "144362.0",
        "PercentFullyVaccinated": "55.621"
    },
    {
        "Description": "Garrett",
        "Value": "",
        "Population": "",
        "FirstDose": "10916",
        "PercentageFirstDose": "37.623",
        "SecondDose": "10019",
        "PercentageSecondDose": "34.532",
        "SingleDose": "802",
        "PercentageSingleDose": "2.764",
        "AtLeastOneVaccine": "11718.0",
        "PercentAtLeastOneVaccine": "40.387",
        "FullyVaccinated": "10821.0",
        "PercentFullyVaccinated": "37.296"
    },
    {
        "Description": "Harford",
        "Value": "",
        "Population": "",
        "FirstDose": "128795",
        "PercentageFirstDose": "50.421",
        "SecondDose": "118321",
        "PercentageSecondDose": "46.32",
        "SingleDose": "11823",
        "PercentageSingleDose": "4.628",
        "AtLeastOneVaccine": "140618.0",
        "PercentAtLeastOneVaccine": "55.049",
        "FullyVaccinated": "130144.0",
        "PercentFullyVaccinated": "50.949"
    },
    {
        "Description": "Howard",
        "Value": "",
        "Population": "",
        "FirstDose": "212978",
        "PercentageFirstDose": "65.393",
        "SecondDose": "196543",
        "PercentageSecondDose": "60.347",
        "SingleDose": "13177",
        "PercentageSingleDose": "4.046",
        "AtLeastOneVaccine": "226155.0",
        "PercentAtLeastOneVaccine": "69.439",
        "FullyVaccinated": "209720.0",
        "PercentFullyVaccinated": "64.393"
    },
    {
        "Description": "Kent",
        "Value": "",
        "Population": "",
        "FirstDose": "9914",
        "PercentageFirstDose": "51.045",
        "SecondDose": "9094",
        "PercentageSecondDose": "46.823",
        "SingleDose": "800",
        "PercentageSingleDose": "4.119",
        "AtLeastOneVaccine": "10714.0",
        "PercentAtLeastOneVaccine": "55.164",
        "FullyVaccinated": "9894.0",
        "PercentFullyVaccinated": "50.942"
    },
    {
        "Description": "Montgomery",
        "Value": "",
        "Population": "",
        "FirstDose": "657800",
        "PercentageFirstDose": "62.607",
        "SecondDose": "596534",
        "PercentageSecondDose": "56.776",
        "SingleDose": "43236",
        "PercentageSingleDose": "4.115",
        "AtLeastOneVaccine": "701036.0",
        "PercentAtLeastOneVaccine": "66.722",
        "FullyVaccinated": "639770.0",
        "PercentFullyVaccinated": "60.891"
    },
    {
        "Description": "Prince George's",
        "Value": "",
        "Population": "",
        "FirstDose": "425916",
        "PercentageFirstDose": "46.839",
        "SecondDose": "373815",
        "PercentageSecondDose": "41.109",
        "SingleDose": "27364",
        "PercentageSingleDose": "3.009",
        "AtLeastOneVaccine": "453280.0",
        "PercentAtLeastOneVaccine": "49.848",
        "FullyVaccinated": "401179.0",
        "PercentFullyVaccinated": "44.118"
    },
    {
        "Description": "Queen Anne's",
        "Value": "",
        "Population": "",
        "FirstDose": "25127",
        "PercentageFirstDose": "49.874",
        "SecondDose": "23150",
        "PercentageSecondDose": "45.95",
        "SingleDose": "2306",
        "PercentageSingleDose": "4.577",
        "AtLeastOneVaccine": "27433.0",
        "PercentAtLeastOneVaccine": "54.451",
        "FullyVaccinated": "25456.0",
        "PercentFullyVaccinated": "50.527"
    },
    {
        "Description": "St. Mary's",
        "Value": "",
        "Population": "",
        "FirstDose": "52043",
        "PercentageFirstDose": "45.849",
        "SecondDose": "48054",
        "PercentageSecondDose": "42.335",
        "SingleDose": "3062",
        "PercentageSingleDose": "2.698",
        "AtLeastOneVaccine": "55105.0",
        "PercentAtLeastOneVaccine": "48.546",
        "FullyVaccinated": "51116.0",
        "PercentFullyVaccinated": "45.032"
    },
    {
        "Description": "Somerset",
        "Value": "",
        "Population": "",
        "FirstDose": "9064",
        "PercentageFirstDose": "35.384",
        "SecondDose": "7864",
        "PercentageSecondDose": "30.7",
        "SingleDose": "848",
        "PercentageSingleDose": "3.31",
        "AtLeastOneVaccine": "9912.0",
        "PercentAtLeastOneVaccine": "38.695",
        "FullyVaccinated": "8712.0",
        "PercentFullyVaccinated": "34.01"
    },
    {
        "Description": "Talbot",
        "Value": "",
        "Population": "",
        "FirstDose": "19889",
        "PercentageFirstDose": "53.492",
        "SecondDose": "18333",
        "PercentageSecondDose": "49.307",
        "SingleDose": "2763",
        "PercentageSingleDose": "7.431",
        "AtLeastOneVaccine": "22652.0",
        "PercentAtLeastOneVaccine": "60.924",
        "FullyVaccinated": "21096.0",
        "PercentFullyVaccinated": "56.739"
    },
    {
        "Description": "Washington",
        "Value": "",
        "Population": "",
        "FirstDose": "56706",
        "PercentageFirstDose": "37.541",
        "SecondDose": "51602",
        "PercentageSecondDose": "34.162",
        "SingleDose": "10010",
        "PercentageSingleDose": "6.627",
        "AtLeastOneVaccine": "66716.0",
        "PercentAtLeastOneVaccine": "44.168",
        "FullyVaccinated": "61612.0",
        "PercentFullyVaccinated": "40.789"
    },
    {
        "Description": "Wicomico",
        "Value": "",
        "Population": "",
        "FirstDose": "41040",
        "PercentageFirstDose": "39.61",
        "SecondDose": "37538",
        "PercentageSecondDose": "36.23",
        "SingleDose": "3491",
        "PercentageSingleDose": "3.369",
        "AtLeastOneVaccine": "44531.0",
        "PercentAtLeastOneVaccine": "42.98",
        "FullyVaccinated": "41029.0",
        "PercentFullyVaccinated": "39.6"
    },
    {
        "Description": "Worcester",
        "Value": "",
        "Population": "",
        "FirstDose": "27609",
        "PercentageFirstDose": "52.814",
        "SecondDose": "25214",
        "PercentageSecondDose": "48.232",
        "SingleDose": "2305",
        "PercentageSingleDose": "4.409",
        "AtLeastOneVaccine": "29914.0",
        "PercentAtLeastOneVaccine": "57.223",
        "FullyVaccinated": "27519.0",
        "PercentFullyVaccinated": "52.642"
    },
    {
        "Description": "Unknown County",
        "Value": "",
        "Population": "",
        "FirstDose": "282483",
        "PercentageFirstDose": "",
        "SecondDose": "231948",
        "PercentageSecondDose": "",
        "SingleDose": "20853",
        "PercentageSingleDose": "",
        "AtLeastOneVaccine": "303336.0",
        "PercentAtLeastOneVaccine": "",
        "FullyVaccinated": "252801.0",
        "PercentFullyVaccinated": ""
    },
    {
        "Description": "Female",
        "Value": "",
        "Population": "",
        "FirstDose": "1806745",
        "PercentageFirstDose": "",
        "SecondDose": "1630308",
        "PercentageSecondDose": "",
        "SingleDose": "121390",
        "PercentageSingleDose": "",
        "AtLeastOneVaccine": null,
        "PercentAtLeastOneVaccine": null,
        "FullyVaccinated": null,
        "PercentFullyVaccinated": null
    },
    {
        "Description": "Male",
        "Value": "",
        "Population": "",
        "FirstDose": "1484497",
        "PercentageFirstDose": "",
        "SecondDose": "1324044",
        "PercentageSecondDose": "",
        "SingleDose": "130288",
        "PercentageSingleDose": "",
        "AtLeastOneVaccine": null,
        "PercentAtLeastOneVaccine": null,
        "FullyVaccinated": null,
        "PercentFullyVaccinated": null
    },
    {
        "Description": "Unknown Gender",
        "Value": "",
        "Population": "",
        "FirstDose": "23407",
        "PercentageFirstDose": "",
        "SecondDose": "21269",
        "PercentageSecondDose": "",
        "SingleDose": "2181",
        "PercentageSingleDose": "",
        "AtLeastOneVaccine": null,
        "PercentAtLeastOneVaccine": null,
        "FullyVaccinated": null,
        "PercentFullyVaccinated": null
    },
    {
        "Description": "American Indian or Alaska Native",
        "Value": "",
        "Population": "",
        "FirstDose": "25580",
        "PercentageFirstDose": "",
        "SecondDose": "22720",
        "PercentageSecondDose": "",
        "SingleDose": "1424",
        "PercentageSingleDose": "",
        "AtLeastOneVaccine": null,
        "PercentAtLeastOneVaccine": null,
        "FullyVaccinated": null,
        "PercentFullyVaccinated": null
    },
    {
        "Description": "Asian",
        "Value": "",
        "Population": "",
        "FirstDose": "254156",
        "PercentageFirstDose": "",
        "SecondDose": "231216",
        "PercentageSecondDose": "",
        "SingleDose": "12798",
        "PercentageSingleDose": "",
        "AtLeastOneVaccine": null,
        "PercentAtLeastOneVaccine": null,
        "FullyVaccinated": null,
        "PercentFullyVaccinated": null
    },
    {
        "Description": "Black or African American",
        "Value": "",
        "Population": "",
        "FirstDose": "801586",
        "PercentageFirstDose": "",
        "SecondDose": "699079",
        "PercentageSecondDose": "",
        "SingleDose": "51139",
        "PercentageSingleDose": "",
        "AtLeastOneVaccine": null,
        "PercentAtLeastOneVaccine": null,
        "FullyVaccinated": null,
        "PercentFullyVaccinated": null
    },
    {
        "Description": "Native Hawaiian or Other Pacific Islander",
        "Value": "",
        "Population": "",
        "FirstDose": "8363",
        "PercentageFirstDose": "",
        "SecondDose": "7332",
        "PercentageSecondDose": "",
        "SingleDose": "551",
        "PercentageSingleDose": "",
        "AtLeastOneVaccine": null,
        "PercentAtLeastOneVaccine": null,
        "FullyVaccinated": null,
        "PercentFullyVaccinated": null
    },
    {
        "Description": "White",
        "Value": "",
        "Population": "",
        "FirstDose": "1773266",
        "PercentageFirstDose": "",
        "SecondDose": "1630875",
        "PercentageSecondDose": "",
        "SingleDose": "146498",
        "PercentageSingleDose": "",
        "AtLeastOneVaccine": null,
        "PercentAtLeastOneVaccine": null,
        "FullyVaccinated": null,
        "PercentFullyVaccinated": null
    },
    {
        "Description": "Other Race",
        "Value": "",
        "Population": "",
        "FirstDose": "260652",
        "PercentageFirstDose": "",
        "SecondDose": "215623",
        "PercentageSecondDose": "",
        "SingleDose": "16499",
        "PercentageSingleDose": "",
        "AtLeastOneVaccine": null,
        "PercentAtLeastOneVaccine": null,
        "FullyVaccinated": null,
        "PercentFullyVaccinated": null
    },
    {
        "Description": "Unknown Race",
        "Value": "",
        "Population": "",
        "FirstDose": "191046",
        "PercentageFirstDose": "",
        "SecondDose": "168776",
        "PercentageSecondDose": "",
        "SingleDose": "24950",
        "PercentageSingleDose": "",
        "AtLeastOneVaccine": null,
        "PercentAtLeastOneVaccine": null,
        "FullyVaccinated": null,
        "PercentFullyVaccinated": null
    },
    {
        "Description": "Hispanic or Latino",
        "Value": "",
        "Population": "",
        "FirstDose": "291126",
        "PercentageFirstDose": "",
        "SecondDose": "240155",
        "PercentageSecondDose": "",
        "SingleDose": "21144",
        "PercentageSingleDose": "",
        "AtLeastOneVaccine": null,
        "PercentAtLeastOneVaccine": null,
        "FullyVaccinated": null,
        "PercentFullyVaccinated": null
    },
    {
        "Description": "Not Hispanic or Latino",
        "Value": "",
        "Population": "",
        "FirstDose": "2823583",
        "PercentageFirstDose": "",
        "SecondDose": "2566795",
        "PercentageSecondDose": "",
        "SingleDose": "210064",
        "PercentageSingleDose": "",
        "AtLeastOneVaccine": null,
        "PercentAtLeastOneVaccine": null,
        "FullyVaccinated": null,
        "PercentFullyVaccinated": null
    },
    {
        "Description": "Unknown Ethnicity",
        "Value": "",
        "Population": "",
        "FirstDose": "199940",
        "PercentageFirstDose": "",
        "SecondDose": "168671",
        "PercentageSecondDose": "",
        "SingleDose": "22651",
        "PercentageSingleDose": "",
        "AtLeastOneVaccine": null,
        "PercentAtLeastOneVaccine": null,
        "FullyVaccinated": null,
        "PercentFullyVaccinated": null
    },
    {
        "Description": "0-9",
        "Value": "",
        "Population": "",
        "FirstDose": "0",
        "PercentageFirstDose": "",
        "SecondDose": "0",
        "PercentageSecondDose": "",
        "SingleDose": "0",
        "PercentageSingleDose": "",
        "AtLeastOneVaccine": "",
        "PercentAtLeastOneVaccine": "",
        "FullyVaccinated": "0",
        "PercentFullyVaccinated": "",
        "null": [
            "0"
        ]
    },
    {
        "Description": "10-19",
        "Value": "",
        "Population": "",
        "FirstDose": "298268",
        "PercentageFirstDose": "",
        "SecondDose": "242710",
        "PercentageSecondDose": "",
        "SingleDose": "6496",
        "PercentageSingleDose": "",
        "AtLeastOneVaccine": "304764",
        "PercentAtLeastOneVaccine": "",
        "FullyVaccinated": "249206",
        "PercentFullyVaccinated": null
    },
    {
        "Description": "20-29",
        "Value": "",
        "Population": "",
        "FirstDose": "402315",
        "PercentageFirstDose": "",
        "SecondDose": "347966",
        "PercentageSecondDose": "",
        "SingleDose": "32585",
        "PercentageSingleDose": "",
        "AtLeastOneVaccine": "434900",
        "PercentAtLeastOneVaccine": "",
        "FullyVaccinated": "380551",
        "PercentFullyVaccinated": null
    },
    {
        "Description": "30-39",
        "Value": "",
        "Population": "",
        "FirstDose": "486425",
        "PercentageFirstDose": "",
        "SecondDose": "431241",
        "PercentageSecondDose": "",
        "SingleDose": "40403",
        "PercentageSingleDose": "",
        "AtLeastOneVaccine": "526828",
        "PercentAtLeastOneVaccine": "",
        "FullyVaccinated": "471644",
        "PercentFullyVaccinated": null
    },
    {
        "Description": "40-49",
        "Value": "",
        "Population": "",
        "FirstDose": "485895",
        "PercentageFirstDose": "",
        "SecondDose": "437058",
        "PercentageSecondDose": "",
        "SingleDose": "42660",
        "PercentageSingleDose": "",
        "AtLeastOneVaccine": "528555",
        "PercentAtLeastOneVaccine": "",
        "FullyVaccinated": "479718",
        "PercentFullyVaccinated": null
    },
    {
        "Description": "50-59",
        "Value": "",
        "Population": "",
        "FirstDose": "560195",
        "PercentageFirstDose": "",
        "SecondDose": "509745",
        "PercentageSecondDose": "",
        "SingleDose": "55835",
        "PercentageSingleDose": "",
        "AtLeastOneVaccine": "616030",
        "PercentAtLeastOneVaccine": "",
        "FullyVaccinated": "565580",
        "PercentFullyVaccinated": null
    },
    {
        "Description": "60-69",
        "Value": "",
        "Population": "",
        "FirstDose": "542734",
        "PercentageFirstDose": "",
        "SecondDose": "504006",
        "PercentageSecondDose": "",
        "SingleDose": "47831",
        "PercentageSingleDose": "",
        "AtLeastOneVaccine": "590565",
        "PercentAtLeastOneVaccine": "",
        "FullyVaccinated": "551837",
        "PercentFullyVaccinated": null
    },
    {
        "Description": "70-79",
        "Value": "",
        "Population": "",
        "FirstDose": "352910",
        "PercentageFirstDose": "",
        "SecondDose": "330259",
        "PercentageSecondDose": "",
        "SingleDose": "20568",
        "PercentageSingleDose": "",
        "AtLeastOneVaccine": "373478",
        "PercentAtLeastOneVaccine": "",
        "FullyVaccinated": "350827",
        "PercentFullyVaccinated": null
    },
    {
        "Description": "80+",
        "Value": "",
        "Population": "",
        "FirstDose": "177907",
        "PercentageFirstDose": "",
        "SecondDose": "164636",
        "PercentageSecondDose": "",
        "SingleDose": "7481",
        "PercentageSingleDose": "",
        "AtLeastOneVaccine": "185388",
        "PercentAtLeastOneVaccine": "",
        "FullyVaccinated": "172117",
        "PercentFullyVaccinated": null
    },
    {
        "Description": "Not Available",
        "Value": "",
        "Population": "",
        "FirstDose": "8000",
        "PercentageFirstDose": "",
        "SecondDose": "8000",
        "PercentageSecondDose": "",
        "SingleDose": "0",
        "PercentageSingleDose": "",
        "AtLeastOneVaccine": "8000",
        "PercentAtLeastOneVaccine": "",
        "FullyVaccinated": "0",
        "PercentFullyVaccinated": null
    },
    {
        "Description": "Federal Entities",
        "Value": "",
        "Population": "",
        "FirstDose": "110712",
        "PercentageFirstDose": "",
        "SecondDose": "97352",
        "PercentageSecondDose": "",
        "SingleDose": "3170",
        "PercentageSingleDose": "",
        "AtLeastOneVaccine": "113882",
        "PercentAtLeastOneVaccine": "",
        "FullyVaccinated": "100522",
        "PercentFullyVaccinated": null
    }
]