[
    {
        "Description": "FirstDoseDelta",
        "Value": "25841",
        "Population": "",
        "FirstDose": "",
        "PercentageFirstDose": "",
        "SecondDose": "",
        "PercentageSecondDose": "",
        "SingleDose": null,
        "PercentageSingleDose": null
    },
    {
        "Description": "SecondDoseDelta",
        "Value": "29111",
        "Population": "",
        "FirstDose": "",
        "PercentageFirstDose": "",
        "SecondDose": "",
        "PercentageSecondDose": "",
        "SingleDose": null,
        "PercentageSingleDose": null
    },
    {
        "Description": "SingleDoseDelta",
        "Value": "25",
        "Population": "",
        "FirstDose": "",
        "PercentageFirstDose": "",
        "SecondDose": "",
        "PercentageSecondDose": "",
        "SingleDose": null,
        "PercentageSingleDose": null
    },
    {
        "Description": "FirstDoseDelivered",
        "Value": "1994235",
        "Population": "",
        "FirstDose": "",
        "PercentageFirstDose": "",
        "SecondDose": "",
        "PercentageSecondDose": "",
        "SingleDose": null,
        "PercentageSingleDose": null
    },
    {
        "Description": "SecondDoseDelivered",
        "Value": "1617125",
        "Population": "",
        "FirstDose": "",
        "PercentageFirstDose": "",
        "SecondDose": "",
        "PercentageSecondDose": "",
        "SingleDose": null,
        "PercentageSingleDose": null
    },
    {
        "Description": "TotalSingleDoseDelivered",
        "Value": "196600",
        "Population": "",
        "FirstDose": "",
        "PercentageFirstDose": "",
        "SecondDose": "",
        "PercentageSecondDose": "",
        "SingleDose": null,
        "PercentageSingleDose": null
    },
    {
        "Description": "TotalVaccineDosesDelivered",
        "Value": "3807960",
        "Population": "",
        "FirstDose": "",
        "PercentageFirstDose": "",
        "SecondDose": "",
        "PercentageSecondDose": "",
        "SingleDose": null,
        "PercentageSingleDose": null
    },
    {
        "Description": "FirstDoseDistributed",
        "Value": "2340897",
        "Population": "",
        "FirstDose": "",
        "PercentageFirstDose": "",
        "SecondDose": "",
        "PercentageSecondDose": "",
        "SingleDose": null,
        "PercentageSingleDose": null
    },
    {
        "Description": "FirstDosePercentVaccinated",
        "Value": "38.72",
        "Population": "",
        "FirstDose": "",
        "PercentageFirstDose": "",
        "SecondDose": "",
        "PercentageSecondDose": "",
        "SingleDose": null,
        "PercentageSingleDose": null
    },
    {
        "Description": "SecondDoseCumulative",
        "Value": "1470414",
        "Population": "",
        "FirstDose": "",
        "PercentageFirstDose": "",
        "SecondDose": "",
        "PercentageSecondDose": "",
        "SingleDose": null,
        "PercentageSingleDose": null
    },
    {
        "Description": "SecondDosePercentVaccinated",
        "Value": "24.322",
        "Population": "",
        "FirstDose": "",
        "PercentageFirstDose": "",
        "SecondDose": "",
        "PercentageSecondDose": "",
        "SingleDose": null,
        "PercentageSingleDose": null
    },
    {
        "Description": "SingleDoseDistributed",
        "Value": "179758",
        "Population": "",
        "FirstDose": "",
        "PercentageFirstDose": "",
        "SecondDose": "",
        "PercentageSecondDose": "",
        "SingleDose": null,
        "PercentageSingleDose": null
    },
    {
        "Description": "SingleDosePercentVaccinated",
        "Value": "2.973",
        "Population": "",
        "FirstDose": "",
        "PercentageFirstDose": "",
        "SecondDose": "",
        "PercentageSecondDose": "",
        "SingleDose": null,
        "PercentageSingleDose": null
    },
    {
        "Description": "FirstSecondSingleDistributed",
        "Value": "3991069",
        "Population": "",
        "FirstDose": "",
        "PercentageFirstDose": "",
        "SecondDose": "",
        "PercentageSecondDose": "",
        "SingleDose": null,
        "PercentageSingleDose": null
    },
    {
        "Description": "FirstSecondSinglePercentVaccinated",
        "Value": "66.015",
        "Population": "",
        "FirstDose": "",
        "PercentageFirstDose": "",
        "SecondDose": "",
        "PercentageSecondDose": "",
        "SingleDose": null,
        "PercentageSingleDose": null
    },
    {
        "Description": "VaxCompletedDistributed",
        "Value": "1650172",
        "Population": "",
        "FirstDose": "",
        "PercentageFirstDose": "",
        "SecondDose": "",
        "PercentageSecondDose": "",
        "SingleDose": null,
        "PercentageSingleDose": null
    },
    {
        "Description": "FullyVaxCumulativePercentVaccinated",
        "Value": "27.295",
        "Population": "",
        "FirstDose": "",
        "PercentageFirstDose": "",
        "SecondDose": "",
        "PercentageSecondDose": "",
        "SingleDose": null,
        "PercentageSingleDose": null
    },
    {
        "Description": "Allegany",
        "Value": "",
        "Population": "",
        "FirstDose": "21473",
        "PercentageFirstDose": "30.494",
        "SecondDose": "14567",
        "PercentageSecondDose": "20.687",
        "SingleDose": "2110",
        "PercentageSingleDose": "2.996"
    },
    {
        "Description": "Anne Arundel",
        "Value": "",
        "Population": "",
        "FirstDose": "217214",
        "PercentageFirstDose": "37.5",
        "SecondDose": "137930",
        "PercentageSecondDose": "23.812",
        "SingleDose": "14603",
        "PercentageSingleDose": "2.521"
    },
    {
        "Description": "Baltimore",
        "Value": "",
        "Population": "",
        "FirstDose": "322565",
        "PercentageFirstDose": "38.987",
        "SecondDose": "213466",
        "PercentageSecondDose": "25.801",
        "SingleDose": "23332",
        "PercentageSingleDose": "2.82"
    },
    {
        "Description": "Baltimore City",
        "Value": "",
        "Population": "",
        "FirstDose": "192243",
        "PercentageFirstDose": "32.392",
        "SecondDose": "122957",
        "PercentageSecondDose": "20.718",
        "SingleDose": "11179",
        "PercentageSingleDose": "1.884"
    },
    {
        "Description": "Calvert",
        "Value": "",
        "Population": "",
        "FirstDose": "34104",
        "PercentageFirstDose": "36.859",
        "SecondDose": "22601",
        "PercentageSecondDose": "24.427",
        "SingleDose": "1770",
        "PercentageSingleDose": "1.913"
    },
    {
        "Description": "Caroline",
        "Value": "",
        "Population": "",
        "FirstDose": "9469",
        "PercentageFirstDose": "28.345",
        "SecondDose": "7160",
        "PercentageSecondDose": "21.433",
        "SingleDose": "2182",
        "PercentageSingleDose": "6.532"
    },
    {
        "Description": "Carroll",
        "Value": "",
        "Population": "",
        "FirstDose": "63679",
        "PercentageFirstDose": "37.804",
        "SecondDose": "42405",
        "PercentageSecondDose": "25.174",
        "SingleDose": "6230",
        "PercentageSingleDose": "3.698"
    },
    {
        "Description": "Cecil",
        "Value": "",
        "Population": "",
        "FirstDose": "28779",
        "PercentageFirstDose": "27.98",
        "SecondDose": "20029",
        "PercentageSecondDose": "19.473",
        "SingleDose": "1769",
        "PercentageSingleDose": "1.72"
    },
    {
        "Description": "Charles",
        "Value": "",
        "Population": "",
        "FirstDose": "49859",
        "PercentageFirstDose": "30.54",
        "SecondDose": "31760",
        "PercentageSecondDose": "19.454",
        "SingleDose": "2902",
        "PercentageSingleDose": "1.778"
    },
    {
        "Description": "Dorchester",
        "Value": "",
        "Population": "",
        "FirstDose": "10054",
        "PercentageFirstDose": "31.489",
        "SecondDose": "7261",
        "PercentageSecondDose": "22.741",
        "SingleDose": "1617",
        "PercentageSingleDose": "5.064"
    },
    {
        "Description": "Frederick",
        "Value": "",
        "Population": "",
        "FirstDose": "99035",
        "PercentageFirstDose": "38.157",
        "SecondDose": "60805",
        "PercentageSecondDose": "23.427",
        "SingleDose": "12053",
        "PercentageSingleDose": "4.644"
    },
    {
        "Description": "Garrett",
        "Value": "",
        "Population": "",
        "FirstDose": "9247",
        "PercentageFirstDose": "31.871",
        "SecondDose": "6339",
        "PercentageSecondDose": "21.848",
        "SingleDose": "538",
        "PercentageSingleDose": "1.854"
    },
    {
        "Description": "Harford",
        "Value": "",
        "Population": "",
        "FirstDose": "94449",
        "PercentageFirstDose": "36.975",
        "SecondDose": "61286",
        "PercentageSecondDose": "23.992",
        "SingleDose": "8856",
        "PercentageSingleDose": "3.467"
    },
    {
        "Description": "Howard",
        "Value": "",
        "Population": "",
        "FirstDose": "152919",
        "PercentageFirstDose": "46.952",
        "SecondDose": "98097",
        "PercentageSecondDose": "30.12",
        "SingleDose": "10078",
        "PercentageSingleDose": "3.094"
    },
    {
        "Description": "Kent",
        "Value": "",
        "Population": "",
        "FirstDose": "7975",
        "PercentageFirstDose": "41.062",
        "SecondDose": "5435",
        "PercentageSecondDose": "27.984",
        "SingleDose": "539",
        "PercentageSingleDose": "2.775"
    },
    {
        "Description": "Montgomery",
        "Value": "",
        "Population": "",
        "FirstDose": "460824",
        "PercentageFirstDose": "43.859",
        "SecondDose": "273820",
        "PercentageSecondDose": "26.061",
        "SingleDose": "32325",
        "PercentageSingleDose": "3.077"
    },
    {
        "Description": "Prince George's",
        "Value": "",
        "Population": "",
        "FirstDose": "281599",
        "PercentageFirstDose": "30.968",
        "SecondDose": "160574",
        "PercentageSecondDose": "17.659",
        "SingleDose": "17775",
        "PercentageSingleDose": "1.955"
    },
    {
        "Description": "Queen Anne's",
        "Value": "",
        "Population": "",
        "FirstDose": "19315",
        "PercentageFirstDose": "38.338",
        "SecondDose": "13004",
        "PercentageSecondDose": "19.323",
        "SingleDose": "1586",
        "PercentageSingleDose": "3.148"
    },
    {
        "Description": "St. Mary's",
        "Value": "",
        "Population": "",
        "FirstDose": "37719",
        "PercentageFirstDose": "33.23",
        "SecondDose": "24856",
        "PercentageSecondDose": "21.898",
        "SingleDose": "1700",
        "PercentageSingleDose": "1.498"
    },
    {
        "Description": "Somerset",
        "Value": "",
        "Population": "",
        "FirstDose": "5973",
        "PercentageFirstDose": "23.317",
        "SecondDose": "4362",
        "PercentageSecondDose": "17.028",
        "SingleDose": "556",
        "PercentageSingleDose": "2.171"
    },
    {
        "Description": "Talbot",
        "Value": "",
        "Population": "",
        "FirstDose": "16559",
        "PercentageFirstDose": "44.536",
        "SecondDose": "11962",
        "PercentageSecondDose": "32.172",
        "SingleDose": "2113",
        "PercentageSingleDose": "5.683"
    },
    {
        "Description": "Washington",
        "Value": "",
        "Population": "",
        "FirstDose": "39636",
        "PercentageFirstDose": "26.24",
        "SecondDose": "29187",
        "PercentageSecondDose": "19.323",
        "SingleDose": "8070",
        "PercentageSingleDose": "5.343"
    },
    {
        "Description": "Wicomico",
        "Value": "",
        "Population": "",
        "FirstDose": "33081",
        "PercentageFirstDose": "31.929",
        "SecondDose": "24463",
        "PercentageSecondDose": "23.611",
        "SingleDose": "2392",
        "PercentageSingleDose": "2.309"
    },
    {
        "Description": "Worcester",
        "Value": "",
        "Population": "",
        "FirstDose": "22335",
        "PercentageFirstDose": "42.725",
        "SecondDose": "16501",
        "PercentageSecondDose": "31.565",
        "SingleDose": "1629",
        "PercentageSingleDose": "3.116"
    },
    {
        "Description": "Unknown County",
        "Value": "",
        "Population": "",
        "FirstDose": "110792",
        "PercentageFirstDose": "",
        "SecondDose": "59587",
        "PercentageSecondDose": "",
        "SingleDose": "11854",
        "PercentageSingleDose": ""
    },
    {
        "Description": "Female",
        "Value": "",
        "Population": "",
        "FirstDose": "1319763",
        "PercentageFirstDose": "",
        "SecondDose": "862156",
        "PercentageSecondDose": "",
        "SingleDose": "92878",
        "PercentageSingleDose": ""
    },
    {
        "Description": "Male",
        "Value": "",
        "Population": "",
        "FirstDose": "1008121",
        "PercentageFirstDose": "",
        "SecondDose": "600897",
        "PercentageSecondDose": "",
        "SingleDose": "85160",
        "PercentageSingleDose": ""
    },
    {
        "Description": "Unknown Gender",
        "Value": "",
        "Population": "",
        "FirstDose": "13013",
        "PercentageFirstDose": "",
        "SecondDose": "7361",
        "PercentageSecondDose": "",
        "SingleDose": "1720",
        "PercentageSingleDose": ""
    },
    {
        "Description": "American Indian or Alaska Native",
        "Value": "",
        "Population": "",
        "FirstDose": "17014",
        "PercentageFirstDose": "",
        "SecondDose": "9834",
        "PercentageSecondDose": "",
        "SingleDose": "1033",
        "PercentageSingleDose": ""
    },
    {
        "Description": "Asian",
        "Value": "",
        "Population": "",
        "FirstDose": "172931",
        "PercentageFirstDose": "",
        "SecondDose": "95640",
        "PercentageSecondDose": "",
        "SingleDose": "9719",
        "PercentageSingleDose": ""
    },
    {
        "Description": "Black or African American",
        "Value": "",
        "Population": "",
        "FirstDose": "522253",
        "PercentageFirstDose": "",
        "SecondDose": "317103",
        "PercentageSecondDose": "",
        "SingleDose": "35672",
        "PercentageSingleDose": ""
    },
    {
        "Description": "Native Hawaiian or Other Pacific Islander",
        "Value": "",
        "Population": "",
        "FirstDose": "5267",
        "PercentageFirstDose": "",
        "SecondDose": "2953",
        "PercentageSecondDose": "",
        "SingleDose": "371",
        "PercentageSingleDose": ""
    },
    {
        "Description": "White",
        "Value": "",
        "Population": "",
        "FirstDose": "1358021",
        "PercentageFirstDose": "",
        "SecondDose": "910034",
        "PercentageSecondDose": "",
        "SingleDose": "104471",
        "PercentageSingleDose": ""
    },
    {
        "Description": "Other Race",
        "Value": "",
        "Population": "",
        "FirstDose": "141034",
        "PercentageFirstDose": "",
        "SecondDose": "76950",
        "PercentageSecondDose": "",
        "SingleDose": "9312",
        "PercentageSingleDose": ""
    },
    {
        "Description": "Unknown Race",
        "Value": "",
        "Population": "",
        "FirstDose": "124377",
        "PercentageFirstDose": "",
        "SecondDose": "57900",
        "PercentageSecondDose": "",
        "SingleDose": "19180",
        "PercentageSingleDose": ""
    },
    {
        "Description": "Hispanic or Latino",
        "Value": "",
        "Population": "",
        "FirstDose": "139206",
        "PercentageFirstDose": "",
        "SecondDose": "67356",
        "PercentageSecondDose": "",
        "SingleDose": "11673",
        "PercentageSingleDose": ""
    },
    {
        "Description": "Not Hispanic or Latino",
        "Value": "",
        "Population": "",
        "FirstDose": "2063289",
        "PercentageFirstDose": "",
        "SecondDose": "1343584",
        "PercentageSecondDose": "",
        "SingleDose": "152008",
        "PercentageSingleDose": ""
    },
    {
        "Description": "Unknown Ethnicity",
        "Value": "",
        "Population": "",
        "FirstDose": "138402",
        "PercentageFirstDose": "",
        "SecondDose": "59474",
        "PercentageSecondDose": "",
        "SingleDose": "16077",
        "PercentageSingleDose": ""
    },
    {
        "Description": "0-9",
        "Value": "",
        "Population": "",
        "FirstDose": "0",
        "PercentageFirstDose": "",
        "SecondDose": "0",
        "PercentageSecondDose": "",
        "SingleDose": "0",
        "PercentageSingleDose": ""
    },
    {
        "Description": "10-19",
        "Value": "",
        "Population": "",
        "FirstDose": "64517",
        "PercentageFirstDose": "",
        "SecondDose": "15014",
        "PercentageSecondDose": "",
        "SingleDose": "3874",
        "PercentageSingleDose": ""
    },
    {
        "Description": "20-29",
        "Value": "",
        "Population": "",
        "FirstDose": "246072",
        "PercentageFirstDose": "",
        "SecondDose": "123012",
        "PercentageSecondDose": "",
        "SingleDose": "20344",
        "PercentageSingleDose": ""
    },
    {
        "Description": "30-39",
        "Value": "",
        "Population": "",
        "FirstDose": "326784",
        "PercentageFirstDose": "",
        "SecondDose": "181008",
        "PercentageSecondDose": "",
        "SingleDose": "26803",
        "PercentageSingleDose": ""
    },
    {
        "Description": "40-49",
        "Value": "",
        "Population": "",
        "FirstDose": "338168",
        "PercentageFirstDose": "",
        "SecondDose": "188968",
        "PercentageSecondDose": "",
        "SingleDose": "29480",
        "PercentageSingleDose": ""
    },
    {
        "Description": "50-59",
        "Value": "",
        "Population": "",
        "FirstDose": "412334",
        "PercentageFirstDose": "",
        "SecondDose": "227394",
        "PercentageSecondDose": "",
        "SingleDose": "40092",
        "PercentageSingleDose": ""
    },
    {
        "Description": "60-69",
        "Value": "",
        "Population": "",
        "FirstDose": "463276",
        "PercentageFirstDose": "",
        "SecondDose": "317031",
        "PercentageSecondDose": "",
        "SingleDose": "37201",
        "PercentageSingleDose": ""
    },
    {
        "Description": "70-79",
        "Value": "",
        "Population": "",
        "FirstDose": "324123",
        "PercentageFirstDose": "",
        "SecondDose": "275328",
        "PercentageSecondDose": "",
        "SingleDose": "16378",
        "PercentageSingleDose": ""
    },
    {
        "Description": "80+",
        "Value": "",
        "Population": "",
        "FirstDose": "165627",
        "PercentageFirstDose": "",
        "SecondDose": "142659",
        "PercentageSecondDose": "",
        "SingleDose": "5586",
        "PercentageSingleDose": ""
    },
    {
        "Description": "Not Available",
        "Value": "",
        "Population": "",
        "FirstDose": "8000",
        "PercentageFirstDose": "",
        "SecondDose": "0",
        "PercentageSecondDose": "",
        "SingleDose": "0",
        "PercentageSingleDose": ""
    }
]